{
    "version": "2.0.0",
    "main": "",

    "system": {
      "localization": true
    },
  
    "properties": [
      {
        "id": "qichatFileName",
        "name": "File Name",
        "locale_name": {
          "fr_FR": "Nom du fichier"
        },  
        "type": "String",
        "value": "product_info_enu.top"
      }
    ],
  
    "events": [
      {
        "id": "humanIsEngaged",
        "name": "Human is engaged",
        "locale_name": {
          "fr_FR": "Humain engagé"
        }
      },
      {
        "id": "qiChatStarted",
        "name": "Qi Chat Started",
        "locale_name": {
          "fr_FR": "Qi Chat commencé"
        }
      }
    ],
  
    "actions": [
      {
        "id": "say",
        "name": "Say",
        "locale_name": {
          "fr_FR": "Parle"
        },
        "params": [
          {
            "id": "text",
            "name": "Text",
            "locale_name": {
              "fr_FR": "Texte"
            },
            "type": "String",
            "value": "Hello!"
          }
        ]
      },
      {
        "id": "setVariable",
        "name": "Set Variable",
        "locale_name": {
          "fr_FR": "Définir la variable"
        },
        "params": [
          {
            "id": "name",
            "name": "Variable Name",
            "locale_name": {
              "fr_FR": "Nom de la variable"
            },
            "type": "String",
            "value": ""
          },
          {
            "id": "value",
            "name": "Variable Value",
            "locale_name": {
              "fr_FR": "Valeur de la variable"
            },
            "type": "String",
            "value": "",
            "bindable": true
          }
        ]
      },
      {
        "id": "startQiChat",
        "name": "Start QiChat",
        "locale_name": {
          "fr_FR": "Démarrer le QiChat"
        }
      },
      {
        "id": "stopQiChat",
        "name": "Stop QiChat",
        "locale_name": {
          "fr_FR": "Arrêter le QiChat"
        }
      },
      {
        "id": "startQiAnim",
        "name": "Start QiAnim",
        "locale_name": {
          "fr_FR": "Démarrer la QiAnim"
        },
        "params": [
          {
            "id": "text",
            "name": "Animation",
            "type": "Dropdown",
            "value": "hello_a001",
            "items": [
              {
                "id": "affirmation_a001",
                "name": "Affirmation A001"
              },
              {
                "id": "affirmation_a002",
                "name": "Affirmation A002"
              },
              {
                "id": "affirmation_a003",
                "name": "Affirmation A003"
              },
              {
                "id": "affirmation_a004",
                "name": "Affirmation A004"
              },
              {
                "id": "affirmation_a005",
                "name": "Affirmation A005"
              },
              {
                "id": "affirmation_a006",
                "name": "Affirmation A006"
              },
              {
                "id": "affirmation_a007",
                "name": "Affirmation A007"
              },
              {
                "id": "affirmation_a008",
                "name": "Affirmation A008"
              },
              {
                "id": "affirmation_a009",
                "name": "Affirmation A009"
              },
              {
                "id": "affirmation_a010",
                "name": "Affirmation A010"
              },
              {
                "id": "affirmation_a011",
                "name": "Affirmation A011"
              },
              {
                "id": "affirmation_right_hand_a001",
                "name": "Affirmation Right Hand A001"
              },
              {
                "id": "annoyed_b001",
                "name": "Annoyed B001"
              },
              {
                "id": "annoyed_b002",
                "name": "Annoyed B002"
              },
              {
                "id": "baseball_a001",
                "name": "Baseball A001"
              },
              {
                "id": "basketball_a001",
                "name": "Basketball A001"
              },
              {
                "id": "bored_a001",
                "name": "Bored A001"
              },
              {
                "id": "both_hands_high_b001",
                "name": "Both Hands High B001"
              },
              {
                "id": "both_hands_in_front_b001",
                "name": "Both Hands In Front B001"
              },
              {
                "id": "both_hands_low_b001",
                "name": "Both Hands Low B001"
              },
              {
                "id": "both_hands_on_hips_b001",
                "name": "Both Hands On Hips B001"
              },
              {
                "id": "bow_a001",
                "name": "Bow A001"
              },
              {
                "id": "bowing_b001",
                "name": "Bowing B001"
              },
              {
                "id": "bowling_a001",
                "name": "Bowling A001"
              },
              {
                "id": "cautious_a001",
                "name": "Cautious A001"
              },
              {
                "id": "certain_b001",
                "name": "Certain B001"
              },
              {
                "id": "check_time_left_b001",
                "name": "Check Time Left B001"
              },
              {
                "id": "check_time_right_b001",
                "name": "Check Time Right B001"
              },
              {
                "id": "cheers_b001",
                "name": "Cheers B001"
              },
              {
                "id": "chill_a001",
                "name": "Chill A001"
              },
              {
                "id": "clapping_b001",
                "name": "Clapping B001"
              },
              {
                "id": "confused_a001",
                "name": "Confused A001"
              },
              {
                "id": "coughing_left_b001",
                "name": "Coughing Left B001"
              },
              {
                "id": "coughing_right_b001",
                "name": "Coughing Right B001"
              },
              {
                "id": "curious_a001",
                "name": "Curious A001"
              },
              {
                "id": "dance_b001",
                "name": "Dance B001"
              },
              {
                "id": "dance_b002",
                "name": "Dance B002"
              },
              {
                "id": "dance_b003",
                "name": "Dance B003"
              },
              {
                "id": "dance_b004",
                "name": "Dance B004"
              },
              {
                "id": "dance_b005",
                "name": "Dance B005"
              },
              {
                "id": "deep_breath_b001",
                "name": "Deep Breath B001"
              },
              {
                "id": "deep_breath_b002",
                "name": "Deep Breath B002"
              },
              {
                "id": "disco_a001",
                "name": "Disco A001"
              },
              {
                "id": "dizzy_a001",
                "name": "Dizzy A001"
              },
              {
                "id": "dizzy_a002",
                "name": "Dizzy A002"
              },
              {
                "id": "dog_a001",
                "name": "Dog A001"
              },
              {
                "id": "drink_left_b001",
                "name": "Drink Left B001"
              },
              {
                "id": "drink_right_b001",
                "name": "Drink Right B001"
              },
              {
                "id": "drumroll_b001",
                "name": "Drumroll B001"
              },
              {
                "id": "elephant_a001",
                "name": "Elephant A001"
              },
              {
                "id": "enumeration_both_hand_a001",
                "name": "Enumeration Both Hand A001"
              },
              {
                "id": "enumeration_both_hand_a002",
                "name": "Enumeration Both Hand A002"
              },
              {
                "id": "enumeration_both_hand_a003",
                "name": "Enumeration Both Hand A003"
              },
              {
                "id": "enumeration_both_hand_a004",
                "name": "Enumeration Both Hand A004"
              },
              {
                "id": "enumeration_left_hand_a001",
                "name": "Enumeration Left Hand A001"
              },
              {
                "id": "enumeration_left_hand_a002",
                "name": "Enumeration Left Hand A002"
              },
              {
                "id": "enumeration_left_hand_a003",
                "name": "Enumeration Left Hand A003"
              },
              {
                "id": "enumeration_left_hand_a004",
                "name": "Enumeration Left Hand A004"
              },
              {
                "id": "enumeration_right_hand_a001",
                "name": "Enumeration Right Hand A001"
              },
              {
                "id": "evil_a001",
                "name": "Evil A001"
              },
              {
                "id": "exclamation_both_hands_a001",
                "name": "Exclamation Both Hands A001"
              },
              {
                "id": "exclamation_both_hands_a002",
                "name": "Exclamation Both Hands A002"
              },
              {
                "id": "exclamation_both_hands_a003",
                "name": "Exclamation Both Hands A003"
              },
              {
                "id": "exclamation_both_hands_a004",
                "name": "Exclamation Both Hands A004"
              },
              {
                "id": "exclamation_both_hands_a005",
                "name": "Exclamation Both Hands A005"
              },
              {
                "id": "exclamation_both_hands_a006",
                "name": "Exclamation Both Hands A006"
              },
              {
                "id": "exclamation_both_hands_a007",
                "name": "Exclamation Both Hands A007"
              },
              {
                "id": "exclamation_left_hands_a001",
                "name": "Exclamation Left Hands A001"
              },
              {
                "id": "exclamation_left_hands_a002",
                "name": "Exclamation Left Hands A002"
              },
              {
                "id": "fear_a001",
                "name": "Fear A001"
              },
              {
                "id": "feline_a001",
                "name": "Feline A001"
              },
              {
                "id": "flick_down_left_hand_b001",
                "name": "Flick Down Left Hand B001"
              },
              {
                "id": "flick_down_right_hand_b001",
                "name": "Flick Down Right Hand B001"
              },
              {
                "id": "flick_left_left_hand_b001",
                "name": "Flick Left Left Hand B001"
              },
              {
                "id": "flick_right_right_hand_b001",
                "name": "Flick Right Right Hand B001"
              },
              {
                "id": "funny_a001",
                "name": "Funny A001"
              },
              {
                "id": "furious_a001",
                "name": "Furious A001"
              },
              {
                "id": "gesture_both_hands_b001",
                "name": "Gesture Both Hands B001"
              },
              {
                "id": "gesture_left_hand_b001",
                "name": "Gesture Left Hand B001"
              },
              {
                "id": "gesture_right_hand_b001",
                "name": "Gesture Right Hand B001"
              },
              {
                "id": "go_left_hand_b001",
                "name": "Go Left Hand B001"
              },
              {
                "id": "go_left_hand_b002",
                "name": "Go Left Hand B002"
              },
              {
                "id": "go_right_hand_b001",
                "name": "Go Right Hand B001"
              },
              {
                "id": "go_right_hand_b002",
                "name": "Go Right Hand B002"
              },
              {
                "id": "goalkeeper_a001",
                "name": "Goalkeeper A001"
              },
              {
                "id": "golf_a001",
                "name": "Golf A001"
              },
              {
                "id": "gorilla_a001",
                "name": "Gorilla A001"
              },
              {
                "id": "gorilla_b001",
                "name": "Gorilla B001"
              },
              {
                "id": "guitar_a001",
                "name": "Guitar A001"
              },
              {
                "id": "headbang_a001",
                "name": "Headbang A001"
              },
              {
                "id": "hello_a001",
                "name": "Hello A001"
              },
              {
                "id": "hello_a002",
                "name": "Hello A002"
              },
              {
                "id": "hello_a003",
                "name": "Hello A003"
              },
              {
                "id": "hello_a004",
                "name": "Hello A004"
              },
              {
                "id": "hello_a005",
                "name": "Hello A005"
              },
              {
                "id": "hello_a006",
                "name": "Hello A006"
              },
              {
                "id": "hello_a007",
                "name": "Hello A007"
              },
              {
                "id": "hello_a008",
                "name": "Hello A008"
              },
              {
                "id": "hello_a009",
                "name": "Hello A009"
              },
              {
                "id": "hello_a010",
                "name": "Hello A010"
              },
              {
                "id": "itchi_a001",
                "name": "Itchi A001"
              },
              {
                "id": "itchi_a002",
                "name": "Itchi A002"
              },
              {
                "id": "kisses_a001",
                "name": "Kisses A001"
              },
              {
                "id": "kungfu_a001",
                "name": "Kungfu A001"
              },
              {
                "id": "left_hand_high_b001",
                "name": "Left Hand High B001"
              },
              {
                "id": "left_hand_low_b001",
                "name": "Left Hand Low B001"
              },
              {
                "id": "left_hand_to_chest_b001",
                "name": "Left Hand To Chest B001"
              },
              {
                "id": "left_hand_to_mouth_b001",
                "name": "Left Hand To Mouth B001"
              },
              {
                "id": "left_hand_to_mouth_b002",
                "name": "Left Hand To Mouth B002"
              },
              {
                "id": "listen_left_b001",
                "name": "Listen Left B001"
              },
              {
                "id": "listen_right_b001",
                "name": "Listen Right B001"
              },
              {
                "id": "looking_up_left_hand_b001",
                "name": "Looking Up Left Hand B001"
              },
              {
                "id": "looking_up_right_hand_b001",
                "name": "Looking Up Right Hand B001"
              },
              {
                "id": "make_space_a001",
                "name": "Make Space A001"
              },
              {
                "id": "make_space_a002",
                "name": "Make Space A002"
              },
              {
                "id": "make_space_a003",
                "name": "Make Space A003"
              },
              {
                "id": "make_space_a004",
                "name": "Make Space A004"
              },
              {
                "id": "meditation_a001",
                "name": "Meditation A001"
              },
              {
                "id": "melancholic_a001",
                "name": "Melancholic A001"
              },
              {
                "id": "mouse_a001",
                "name": "Mouse A001"
              },
              {
                "id": "napping_left_b001",
                "name": "Napping Left B001"
              },
              {
                "id": "napping_right_b001",
                "name": "Napping Right B001"
              },
              {
                "id": "negation_both_hands_a001",
                "name": "Negation Both Hands A001"
              },
              {
                "id": "negation_both_hands_a002",
                "name": "Negation Both Hands A002"
              },
              {
                "id": "negation_both_hands_a003",
                "name": "Negation Both Hands A003"
              },
              {
                "id": "negation_both_hands_a004",
                "name": "Negation Both Hands A004"
              },
              {
                "id": "negation_both_hands_a005",
                "name": "Negation Both Hands A005"
              },
              {
                "id": "negation_both_hands_b001",
                "name": "Negation Both Hands B001"
              },
              {
                "id": "negation_both_hands_b002",
                "name": "Negation Both Hands B002"
              },
              {
                "id": "negation_left_hand_a001",
                "name": "Negation Left Hand A001"
              },
              {
                "id": "negation_left_hand_b001",
                "name": "Negation Left Hand B001"
              },
              {
                "id": "negation_left_hand_b002",
                "name": "Negation Left Hand B002"
              },
              {
                "id": "negation_left_hand_b003",
                "name": "Negation Left Hand B003"
              },
              {
                "id": "negation_right_hand_b001",
                "name": "Negation Right Hand B001"
              },
              {
                "id": "negation_right_hand_b002",
                "name": "Negation Right Hand B002"
              },
              {
                "id": "negation_right_hand_b003",
                "name": "Negation Right Hand B003"
              },
              {
                "id": "negation_shake_head_b001",
                "name": "Negation Shake Head B001"
              },
              {
                "id": "nicereaction_a001",
                "name": "Nicereaction A001"
              },
              {
                "id": "nicereaction_a002",
                "name": "Nicereaction A002"
              },
              {
                "id": "open_drink_left_b001",
                "name": "Open Drink Left B001"
              },
              {
                "id": "open_drink_right_b001",
                "name": "Open Drink Right B001"
              },
              {
                "id": "question_both_hand_a001",
                "name": "Question Both Hand A001"
              },
              {
                "id": "question_both_hand_a002",
                "name": "Question Both Hand A002"
              },
              {
                "id": "question_both_hand_a003",
                "name": "Question Both Hand A003"
              },
              {
                "id": "question_both_hand_a004",
                "name": "Question Both Hand A004"
              },
              {
                "id": "question_both_hand_a005",
                "name": "Question Both Hand A005"
              },
              {
                "id": "question_both_hand_a006",
                "name": "Question Both Hand A006"
              },
              {
                "id": "question_both_hand_a007",
                "name": "Question Both Hand A007"
              },
              {
                "id": "question_right_hand_a001",
                "name": "Question Right Hand A001"
              },
              {
                "id": "raise_both_hands_b001",
                "name": "Raise Both Hands B001"
              },
              {
                "id": "raise_both_hands_b002",
                "name": "Raise Both Hands B002"
              },
              {
                "id": "raise_both_hands_b003",
                "name": "Raise Both Hands B003"
              },
              {
                "id": "raise_both_hands_b004",
                "name": "Raise Both Hands B004"
              },
              {
                "id": "raise_left_hand_a001",
                "name": "Raise Left Hand A001"
              },
              {
                "id": "raise_left_hand_a002",
                "name": "Raise Left Hand A002"
              },
              {
                "id": "raise_left_hand_a003",
                "name": "Raise Left Hand A003"
              },
              {
                "id": "raise_left_hand_b001",
                "name": "Raise Left Hand B001"
              },
              {
                "id": "raise_left_hand_b002",
                "name": "Raise Left Hand B002"
              },
              {
                "id": "raise_left_hand_b003",
                "name": "Raise Left Hand B003"
              },
              {
                "id": "raise_left_hand_b004",
                "name": "Raise Left Hand B004"
              },
              {
                "id": "raise_left_hand_b005",
                "name": "Raise Left Hand B005"
              },
              {
                "id": "raise_left_hand_b006",
                "name": "Raise Left Hand B006"
              },
              {
                "id": "raise_left_hand_b007",
                "name": "Raise Left Hand B007"
              },
              {
                "id": "raise_left_hand_b008",
                "name": "Raise Left Hand B008"
              },
              {
                "id": "raise_left_hand_so_a001",
                "name": "Raise Left Hand So A001"
              },
              {
                "id": "raise_right_hand_a001",
                "name": "Raise Right Hand A001"
              },
              {
                "id": "raise_right_hand_a002",
                "name": "Raise Right Hand A002"
              },
              {
                "id": "raise_right_hand_a003",
                "name": "Raise Right Hand A003"
              },
              {
                "id": "raise_right_hand_b001",
                "name": "Raise Right Hand B001"
              },
              {
                "id": "raise_right_hand_b002",
                "name": "Raise Right Hand B002"
              },
              {
                "id": "raise_right_hand_b003",
                "name": "Raise Right Hand B003"
              },
              {
                "id": "raise_right_hand_b004",
                "name": "Raise Right Hand B004"
              },
              {
                "id": "raise_right_hand_b005",
                "name": "Raise Right Hand B005"
              },
              {
                "id": "raise_right_hand_b006",
                "name": "Raise Right Hand B006"
              },
              {
                "id": "raise_right_hand_b007",
                "name": "Raise Right Hand B007"
              },
              {
                "id": "raise_right_hand_b008",
                "name": "Raise Right Hand B008"
              },
              {
                "id": "raise_right_hand_so_a001",
                "name": "Raise Right Hand So A001"
              },
              {
                "id": "right_hand_high_b001",
                "name": "Right Hand High B001"
              },
              {
                "id": "right_hand_low_b001",
                "name": "Right Hand Low B001"
              },
              {
                "id": "right_hand_to_chest_b001",
                "name": "Right Hand To Chest B001"
              },
              {
                "id": "right_hand_to_mouth_b001",
                "name": "Right Hand To Mouth B001"
              },
              {
                "id": "right_hand_to_mouth_b002",
                "name": "Right Hand To Mouth B002"
              },
              {
                "id": "sad_a001",
                "name": "Sad A001"
              },
              {
                "id": "sad_a002",
                "name": "Sad A002"
              },
              {
                "id": "sad_a003",
                "name": "Sad A003"
              },
              {
                "id": "saddened_b001",
                "name": "Saddened B001"
              },
              {
                "id": "saddened_b002",
                "name": "Saddened B002"
              },
              {
                "id": "salute_left_b001",
                "name": "Salute Left B001"
              },
              {
                "id": "salute_right_b001",
                "name": "Salute Right B001"
              },
              {
                "id": "saxophone_a001",
                "name": "Saxophone A001"
              },
              {
                "id": "scratch_back_of_head_left_b001",
                "name": "Scratch Back Of Head Left B001"
              },
              {
                "id": "scratch_back_of_head_right_b001",
                "name": "Scratch Back Of Head Right B001"
              },
              {
                "id": "scratch_top_of_head_left_b001",
                "name": "Scratch Top Of Head Left B001"
              },
              {
                "id": "scratch_top_of_head_right_b001",
                "name": "Scratch Top Of Head Right B001"
              },
              {
                "id": "scuba_a001",
                "name": "Scuba A001"
              },
              {
                "id": "searching_a001",
                "name": "Searching A001"
              },
              {
                "id": "show_body_a001",
                "name": "Show Body A001"
              },
              {
                "id": "show_body_a002",
                "name": "Show Body A002"
              },
              {
                "id": "show_body_a003",
                "name": "Show Body A003"
              },
              {
                "id": "show_bumper_right_a001",
                "name": "Show Bumper Right A001"
              },
              {
                "id": "show_hand_both_a001",
                "name": "Show Hand Both A001"
              },
              {
                "id": "show_hand_both_a002",
                "name": "Show Hand Both A002"
              },
              {
                "id": "show_hand_left_a001",
                "name": "Show Hand Left A001"
              },
              {
                "id": "show_hand_left_a002",
                "name": "Show Hand Left A002"
              },
              {
                "id": "show_head_a001",
                "name": "Show Head A001"
              },
              {
                "id": "show_micro_a001",
                "name": "Show Micro A001"
              },
              {
                "id": "show_self_a001",
                "name": "Show Self A001"
              },
              {
                "id": "show_shoulders_a001",
                "name": "Show Shoulders A001"
              },
              {
                "id": "show_tablet_a001",
                "name": "Show Tablet A001"
              },
              {
                "id": "show_tablet_a002",
                "name": "Show Tablet A002"
              },
              {
                "id": "show_tablet_a003",
                "name": "Show Tablet A003"
              },
              {
                "id": "show_tablet_a004",
                "name": "Show Tablet A004"
              },
              {
                "id": "show_tablet_a005",
                "name": "Show Tablet A005"
              },
              {
                "id": "show_tablet_a006",
                "name": "Show Tablet A006"
              },
              {
                "id": "showmuscles_a001",
                "name": "Showmuscles A001"
              },
              {
                "id": "showmuscles_a002",
                "name": "Showmuscles A002"
              },
              {
                "id": "shy_b001",
                "name": "Shy B001"
              },
              {
                "id": "shy_b002",
                "name": "Shy B002"
              },
              {
                "id": "ski_a001",
                "name": "Ski A001"
              },
              {
                "id": "slide_a001",
                "name": "Slide A001"
              },
              {
                "id": "sneeze_b001",
                "name": "Sneeze B001"
              },
              {
                "id": "sniffing_b001",
                "name": "Sniffing B001"
              },
              {
                "id": "spread_both_hands_a001",
                "name": "Spread Both Hands A001"
              },
              {
                "id": "spread_both_hands_a002",
                "name": "Spread Both Hands A002"
              },
              {
                "id": "spread_both_hands_a003",
                "name": "Spread Both Hands A003"
              },
              {
                "id": "spread_both_hands_b001",
                "name": "Spread Both Hands B001"
              },
              {
                "id": "spread_both_hands_b002",
                "name": "Spread Both Hands B002"
              },
              {
                "id": "spread_both_hands_b003",
                "name": "Spread Both Hands B003"
              },
              {
                "id": "spread_both_hands_b004",
                "name": "Spread Both Hands B004"
              },
              {
                "id": "spread_both_hands_b005",
                "name": "Spread Both Hands B005"
              },
              {
                "id": "spread_both_hands_so_a001",
                "name": "Spread Both Hands So A001"
              },
              {
                "id": "spread_both_hands_so_a002",
                "name": "Spread Both Hands So A002"
              },
              {
                "id": "spread_both_hands_so_a003",
                "name": "Spread Both Hands So A003"
              },
              {
                "id": "surf_a001",
                "name": "Surf A001"
              },
              {
                "id": "surprised_a001",
                "name": "Surprised A001"
              },
              {
                "id": "swim_a001",
                "name": "Swim A001"
              },
              {
                "id": "swim_b001",
                "name": "Swim B001"
              },
              {
                "id": "taichichuan_a001",
                "name": "Taichichuan A001"
              },
              {
                "id": "take_pic_b001",
                "name": "Take Pic B001"
              },
              {
                "id": "take_pic_b002",
                "name": "Take Pic B002"
              },
              {
                "id": "tap_display_left_hand_b001",
                "name": "Tap Display Left Hand B001"
              },
              {
                "id": "tap_display_right_hand_b001",
                "name": "Tap Display Right Hand B001"
              },
              {
                "id": "tap_top_of_head_left_b001",
                "name": "Tap Top Of Head Left B001"
              },
              {
                "id": "tap_top_of_head_right_b001",
                "name": "Tap Top Of Head Right B001"
              },
              {
                "id": "thinking_a001",
                "name": "Thinking A001"
              },
              {
                "id": "thinking_a002",
                "name": "Thinking A002"
              },
              {
                "id": "tickling_a001",
                "name": "Tickling A001"
              },
              {
                "id": "tickling_a002",
                "name": "Tickling A002"
              },
              {
                "id": "walk_run_b001",
                "name": "Walk Run B001"
              },
              {
                "id": "washing_arms_b001",
                "name": "Washing Arms B001"
              },
              {
                "id": "waving_both_hands_b001",
                "name": "Waving Both Hands B001"
              },
              {
                "id": "waving_both_hands_b002",
                "name": "Waving Both Hands B002"
              },
              {
                "id": "waving_both_hands_b003",
                "name": "Waving Both Hands B003"
              },
              {
                "id": "waving_left_b001",
                "name": "Waving Left B001"
              },
              {
                "id": "waving_right_b001",
                "name": "Waving Right B001"
              },
              {
                "id": "wolf_a001",
                "name": "Wolf A001"
              },
              {
                "id": "worried_a001",
                "name": "Worried A001"
              },
              {
                "id": "yeah_b001",
                "name": "Yeah B001"
              }
            ]
          }
        ]
      }
    ],
  
    "resources": [
      {
        "id": "qichat.zip",
        "type": "Zip",
        "localization": true
      }
    ]  
}
  